CPR/CirclePointRoundSourcePure.py
CPR/__init__.py
CPR/圈点圆.py
cprspy-0.1.0.dist-info/LICENSE
cprspy-0.1.0.dist-info/METADATA
cprspy-0.1.0.dist-info/WHEEL
cprspy-0.1.0.dist-info/top_level.txt
cprspy-0.1.0.dist-info/RECORD
