Metadata-Version: 2.1
Name: cprspy
Version: 0.1.0
Summary: Circle-Point-Round Source Pure Python Package
Home-page: https://github.com/lbylzkx/Circle-Point-Round
Author: lbylzkx
Author-email: lbylzkx@outlook.com
Classifier: Programming Language :: Python :: 3
Classifier: License :: OSI Approved :: MIT License
Classifier: Operating System :: OS Independent
Requires-Python: >=3.6
License-File: LICENSE
Requires-Dist: numpy
Requires-Dist: matplotlib
